redis_lru/__init__.py
redis_lru/lru.py
redis_lru/tests.py
redis_lru-0.1.2.dist-info/LICENSE
redis_lru-0.1.2.dist-info/METADATA
redis_lru-0.1.2.dist-info/WHEEL
redis_lru-0.1.2.dist-info/top_level.txt
redis_lru-0.1.2.dist-info/RECORD
