Metadata-Version: 2.1
Name: redis-lru
Version: 0.1.2
Summary: LRU cache for Python. Use Redis as backend. Provides a dictionary-like object as well as a method decorator.
Home-page: https://github.com/leohowell/redis-lru
Author: Leo Howell
Author-email: leohowell.com@gmail.com
License: BSD
Platform: UNKNOWN
Classifier: Development Status :: 4 - Beta
Classifier: Environment :: Console
Classifier: Environment :: Web Environment
Classifier: License :: OSI Approved :: BSD License
Classifier: Programming Language :: Python :: 3
Classifier: Programming Language :: Python :: 3.5
Classifier: Programming Language :: Python :: 3.6
Classifier: Programming Language :: Python :: 3.7
Classifier: Programming Language :: Python :: 3.8
Classifier: Programming Language :: Python :: 3.9
Classifier: Programming Language :: Python :: 3.10
Classifier: Programming Language :: Python :: Implementation :: CPython
Requires-Python: >=3.4
License-File: LICENSE
